pythonvideoannotator_module_contoursimages/__init__.py
pythonvideoannotator_module_contoursimages/contoursimages_window.py
pythonvideoannotator_module_contoursimages/module.py
pythonvideoannotator_module_contoursimages/models/__init__.py
pythonvideoannotator_module_contoursimages/models/video/__init__.py
pythonvideoannotator_module_contoursimages/models/video/objects/__init__.py
pythonvideoannotator_module_contoursimages/models/video/objects/object2d/__init__.py
pythonvideoannotator_module_contoursimages/models/video/objects/object2d/datasets/__init__.py
pythonvideoannotator_module_contoursimages/models/video/objects/object2d/datasets/colorproperties_dataset.py
pythonvideoannotator_module_contoursimages/models/video/objects/object2d/datasets/contours/__init__.py
pythonvideoannotator_module_contoursimages/models/video/objects/object2d/datasets/path/__init__.py
Python_video_annotator_module_contours_images-0.5.28.dist-info/METADATA
Python_video_annotator_module_contours_images-0.5.28.dist-info/WHEEL
Python_video_annotator_module_contours_images-0.5.28.dist-info/top_level.txt
Python_video_annotator_module_contours_images-0.5.28.dist-info/RECORD
