Metadata-Version: 2.1
Name: Python-video-annotator-module-contours-images
Version: 0.5.28
Summary: UNKNOWN
Home-page: https://bitbucket.org/fchampalimaud/pythonvideoannotator-module-controursimages
Author: ['Ricardo Ribeiro']
Author-email: ricardojvr@gmail.com
License: UNKNOWN
Platform: UNKNOWN
